LICENSE
MANIFEST.in
README.md
setup.py
django_pt.egg-info/PKG-INFO
django_pt.egg-info/SOURCES.txt
django_pt.egg-info/dependency_links.txt
django_pt.egg-info/not-zip-safe
django_pt.egg-info/top_level.txt
pt/__init__.py
pt/admin.py
pt/forms.py
pt/models.py
pt/shared.py
pt/urls.py
pt/utils.py
pt/views.py
pt/migrations/0001_initial.py
pt/migrations/__init__.py
pt/static/bootstrap/css/bootstrap-theme.min.css
pt/static/bootstrap/css/bootstrap.css
pt/static/bootstrap/css/bootstrap.min.css
pt/static/bootstrap/fonts/glyphicons-halflings-regular.eot
pt/static/bootstrap/fonts/glyphicons-halflings-regular.svg
pt/static/bootstrap/fonts/glyphicons-halflings-regular.ttf
pt/static/bootstrap/fonts/glyphicons-halflings-regular.woff
pt/static/bootstrap/js/bootstrap.js
pt/static/bootstrap/js/bootstrap.min.js
pt/static/images/Logo_50hgt.png
pt/static/site/css/jquery.tagsinput.css
pt/static/site/css/main.css
pt/static/site/ico/favicon.ico
pt/static/site/js/jquery-2.2.1.min.js
pt/static/site/js/jquery.tagsinput.js
pt/static/site/js/site.js
pt/static/site/js/jquery-ui-1.11.4/index.html
pt/static/site/js/jquery-ui-1.11.4/jquery-ui.css
pt/static/site/js/jquery-ui-1.11.4/jquery-ui.js
pt/static/site/js/jquery-ui-1.11.4/jquery-ui.min.css
pt/static/site/js/jquery-ui-1.11.4/jquery-ui.min.js
pt/static/site/js/jquery-ui-1.11.4/jquery-ui.structure.css
pt/static/site/js/jquery-ui-1.11.4/jquery-ui.structure.min.css
pt/static/site/js/jquery-ui-1.11.4/jquery-ui.theme.css
pt/static/site/js/jquery-ui-1.11.4/jquery-ui.theme.min.css
pt/static/site/js/jquery-ui-1.11.4/external/jquery/jquery.js
pt/static/site/js/jquery-ui-1.11.4/images/ui-bg_diagonals-thick_18_b81900_40x40.png
pt/static/site/js/jquery-ui-1.11.4/images/ui-bg_diagonals-thick_20_666666_40x40.png
pt/static/site/js/jquery-ui-1.11.4/images/ui-bg_flat_10_000000_40x100.png
pt/static/site/js/jquery-ui-1.11.4/images/ui-bg_glass_100_f6f6f6_1x400.png
pt/static/site/js/jquery-ui-1.11.4/images/ui-bg_glass_100_fdf5ce_1x400.png
pt/static/site/js/jquery-ui-1.11.4/images/ui-bg_glass_65_ffffff_1x400.png
pt/static/site/js/jquery-ui-1.11.4/images/ui-bg_gloss-wave_35_f6a828_500x100.png
