Metadata-Version: 1.1
Name: django-pt
Version: 0.1
Summary: A simple, Django-powered project tracking solution.
Home-page: https://github.com/fstraw/django-pt
Author: Brandon Batt
Author-email: brbatt@gmail.com
License: MIT
Platform: UNKNOWN
Classifier: Environment :: Web Environment
Classifier: Framework :: Django
Classifier: Intended Audience :: Developers
Classifier: License :: OSI Approved :: MIT License
Classifier: Operating System :: OS Independent
Classifier: Programming Language :: Python
Classifier: Programming Language :: Python :: 2.7
